api_hunt/__init__.py
api_hunt/add_delete.py
api_hunt/cli.py
api_hunt/core.py
api_hunt/get_repattern_ai.py
api_hunt/patterns.py
apikey_hunter-0.1.3.dist-info/METADATA
apikey_hunter-0.1.3.dist-info/WHEEL
apikey_hunter-0.1.3.dist-info/entry_points.txt
apikey_hunter-0.1.3.dist-info/top_level.txt
apikey_hunter-0.1.3.dist-info/RECORD
