Metadata-Version: 2.1
Name: apikey-hunter
Version: 0.1.3
Summary: Scan staged Git files for secrets like API keys.
Author: Joe Mama
Author-email: Joe Mama <brownpandadev7@gmail.com>
Classifier: Programming Language :: Python :: 3
Classifier: Operating System :: OS Independent
Requires-Python: >=3.7
Requires-Dist: google-genai
Requires-Dist: python-dotenv
Requires-Dist: pydantic
